pyrbo/__init__.py
pyrbo/common.py
pyrbo/jit.py
pyrbo/leaf.py
pyrbo/model.py
pyrbo/unroll.py
pyrbo-19.dist-info/COPYING
pyrbo-19.dist-info/METADATA
pyrbo-19.dist-info/WHEEL
pyrbo-19.dist-info/top_level.txt
pyrbo-19.dist-info/RECORD
