Metadata-Version: 2.1
Name: pyrbo
Version: 19
Summary: Python JIT compiler for near-native performance of low-level arithmetic
Home-page: https://github.com/combatopera/pyrbo
Author: Andrzej Cichocki
Author-email: 3613868+combatopera@users.noreply.github.com
License-File: COPYING
Requires-Dist: foyndation>=12
